pandas_pyarrow/__init__.py
pandas_pyarrow/mappers/__init__.py
pandas_pyarrow/mappers/datetime_mapper.py
pandas_pyarrow/mappers/db_types.py
pandas_pyarrow/mappers/dtype_mapper.py
pandas_pyarrow/mappers/numeric_mapper.py
pandas_pyarrow/pda_converter.py
pandas_pyarrow/reverse_converter.py
pandas_pyarrow-0.2.1.dist-info/LICENSE
pandas_pyarrow-0.2.1.dist-info/METADATA
pandas_pyarrow-0.2.1.dist-info/WHEEL
pandas_pyarrow-0.2.1.dist-info/RECORD
