Metadata-Version: 2.3
Name: pandas-pyarrow
Version: 0.2.1
Summary: A library for switching pandas backend to pyarrow
License: MIT
Keywords: python,pandas,pyarrow,arrow,dataframe,bigquery,pandas-pyarrow,pandas-arrow
Author: DanielAvdar
Author-email: 66269169+DanielAvdar@users.noreply.github.com
Requires-Python: >=3.9,<4
Classifier: Development Status :: 5 - Production/Stable
Classifier: Intended Audience :: Developers
Classifier: Intended Audience :: Science/Research
Classifier: License :: OSI Approved :: MIT License
Classifier: Operating System :: Microsoft :: Windows
Classifier: Operating System :: POSIX :: Linux
Classifier: Operating System :: MacOS
Classifier: Programming Language :: Python :: 3 :: Only
Classifier: Programming Language :: Python :: 3.9
Classifier: Programming Language :: Python :: 3.10
Classifier: Programming Language :: Python :: 3.11
Classifier: Programming Language :: Python :: 3.12
Classifier: Programming Language :: Python :: 3.13
Classifier: Topic :: Software Development :: Libraries
Classifier: Topic :: Software Development :: Libraries :: Python Modules
Classifier: Topic :: Scientific/Engineering :: Information Analysis
Classifier: Topic :: Utilities
Provides-Extra: bigquery
Provides-Extra: db-dtypes
Requires-Dist: db-dtypes (>=1) ; extra == "db-dtypes"
Requires-Dist: pandas (>=2)
Requires-Dist: pandas-gbq (>=0.15.0) ; extra == "bigquery"
Requires-Dist: pyarrow (>=10.0.1)
